LICENSE
MANIFEST.in
README.md
setup.py
imface/__init__.py
imface/__main__.py
imface/main.py
imface.egg-info/PKG-INFO
imface.egg-info/SOURCES.txt
imface.egg-info/dependency_links.txt
imface.egg-info/entry_points.txt
imface.egg-info/requires.txt
imface.egg-info/top_level.txt
imface/utils/__init__.py
imface/utils/deepface_util.py
imface/utils/tools.py