Metadata-Version: 2.1
Name: imface
Version: 0.0.0.4.4
Author: Achmad Alfazari
License: License :: OSI Approved :: MIT License
Classifier: Programming Language :: Python
Requires-Python: >=3.5.5
License-File: LICENSE
